pystrace/__init__.py
pystrace/__main__.py
pystrace/_version.py
pystrace/cli.py
pystrace/config.json
pystrace/test_version.py
pystrace/tracer.py
pystrace-0.0.4.dist-info/LICENSE
pystrace-0.0.4.dist-info/METADATA
pystrace-0.0.4.dist-info/WHEEL
pystrace-0.0.4.dist-info/entry_points.txt
pystrace-0.0.4.dist-info/top_level.txt
pystrace-0.0.4.dist-info/RECORD
