Metadata-Version: 2.1
Name: pystrace
Version: 0.0.4
Summary: Report files opened while executing a command
Home-page: https://github.com/joaompinto/pystrace
Author: João Pinto
Author-email: joao.pinto@vshn.ch
License: BSD-3
License-File: LICENSE
Requires-Dist: file-magic
